tub/__init__.py
tub/__main__.py
tub/info.json
tub/init.py
tub/loop.py
tub/translate.py
tub-0.1.dist-info/LICENSE
tub-0.1.dist-info/METADATA
tub-0.1.dist-info/WHEEL
tub-0.1.dist-info/top_level.txt
tub-0.1.dist-info/RECORD
